examples/.gitignore
examples/demo.ipynb
spm12/__init__.py
spm12/__main__.py
spm12/_dist_ver.py
spm12/amypad_coreg.m
spm12/amypad_coreg_modify_affine.m
spm12/amypad_normw.m
spm12/amypad_resample.m
spm12/amypad_seg.m
spm12/cli.py
spm12/regseg.py
spm12/setup_rt.py
spm12/standalone.py
spm12/utils.py
spm12-2.2.0.dist-info/LICENCE.md
spm12-2.2.0.dist-info/METADATA
spm12-2.2.0.dist-info/WHEEL
spm12-2.2.0.dist-info/entry_points.txt
spm12-2.2.0.dist-info/top_level.txt
spm12-2.2.0.dist-info/RECORD
