Metadata-Version: 2.1
Name: spm12
Version: 2.2.0
Summary: Statistical Parametric Mapping
Maintainer-email: Casper da Costa-Luis <casper.dcl@physics.org>
License: Apache-2.0
Project-URL: documentation, https://github.com/AMYPAD/SPM12/#SPM12
Project-URL: repository, https://github.com/AMYPAD/SPM12
Project-URL: changelog, https://github.com/AMYPAD/SPM12/releases
Project-URL: upstream-project, https://www.fil.ion.ucl.ac.uk/spm
Keywords: fMRI,PET,SPECT,EEG,MEG
Classifier: Development Status :: 4 - Beta
Classifier: Intended Audience :: Developers
Classifier: Intended Audience :: Education
Classifier: Intended Audience :: Healthcare Industry
Classifier: Intended Audience :: Science/Research
Classifier: License :: OSI Approved :: Apache Software License
Classifier: Operating System :: Microsoft :: Windows
Classifier: Operating System :: POSIX :: Linux
Classifier: Programming Language :: Other Scripting Engines
Classifier: Programming Language :: Python :: 3
Classifier: Programming Language :: Python :: 3.7
Classifier: Programming Language :: Python :: 3.8
Classifier: Programming Language :: Python :: 3.9
Classifier: Programming Language :: Python :: 3.10
Classifier: Programming Language :: Python :: 3.11
Classifier: Programming Language :: Python :: 3 :: Only
Classifier: Topic :: Scientific/Engineering :: Medical Science Apps.
Classifier: Topic :: Software Development :: Libraries
Classifier: Topic :: System :: Installation/Setup
Requires-Python: >=3.7
License-File: LICENCE.md
Requires-Dist: argopt
Requires-Dist: miutil[nii,web] >=0.12.0
Requires-Dist: numpy
Requires-Dist: scipy
Requires-Dist: importlib-resources ; python_version < "3.9"
Provides-Extra: demo
Requires-Dist: miutil[plot] >=0.3.0 ; extra == 'demo'
Requires-Dist: matplotlib ; extra == 'demo'
Provides-Extra: dev
Requires-Dist: pytest >=6 ; extra == 'dev'
Requires-Dist: pytest-cov ; extra == 'dev'
Requires-Dist: pytest-timeout ; extra == 'dev'
Requires-Dist: pytest-xdist ; extra == 'dev'
